pybitmex/__init__.py
pybitmex/auth.py
pybitmex/bitmex.py
pybitmex/models.py
pybitmex/rest.py
pybitmex/ws.py
pybitmex-0.5.10.dist-info/LICENSE
pybitmex-0.5.10.dist-info/METADATA
pybitmex-0.5.10.dist-info/WHEEL
pybitmex-0.5.10.dist-info/top_level.txt
pybitmex-0.5.10.dist-info/RECORD
