Metadata-Version: 2.1
Name: pybitmex
Version: 0.5.10
Summary: Websocket and REST client library for BitMEX.
Home-page: https://github.com/yanagisawa-kentaro-777/pybitmex
Author: YANAGISAWA, Kentaro
Author-email: yanagisawa.kentaro@weidenthal.co.jp
License: GNU General Public License v3 (GPLv3)
Keywords: BitMEX,trading,trade,cryptocurrency
Platform: UNKNOWN
Classifier: Development Status :: 4 - Beta
Classifier: License :: OSI Approved :: GNU General Public License v3 (GPLv3)
Classifier: Programming Language :: Python
Classifier: Programming Language :: Python :: 3.6
Classifier: Topic :: Office/Business :: Financial
Classifier: Topic :: Software Development :: Libraries :: Python Modules
Requires-Dist: websocket-client (>=0.56.0)
Requires-Dist: requests (>=2.21.0)
Requires-Dist: python-dateutil (>=2.8.0)
